digitaltwin/__init__.py
digitaltwin/active_obj.py
digitaltwin/box.py
digitaltwin/camera.py
digitaltwin/cube.py
digitaltwin/cylinder.py
digitaltwin/editor.py
digitaltwin/placer.py
digitaltwin/printer.py
digitaltwin/render.py
digitaltwin/robot.py
digitaltwin/scene.py
digitaltwin/stacker.py
digitaltwin/workflow.py
digitaltwin/end_effector/__init__.py
digitaltwin/end_effector/gripper.py
digitaltwin/end_effector/suction.py
digitaltwin_data/__init__.py
digitaltwin_data/__pycache__/__init__.cpython-311.pyc
digitaltwin_data/__pycache__/__init__.cpython-39.pyc
digitaltwin_data/cameras/camera3d/camera3d.mtl
digitaltwin_data/cameras/camera3d/camera3d.obj
digitaltwin_data/cameras/camera3d/camera3d.urdf
digitaltwin_data/cameras/camera3d/camera3d_inv.urdf
digitaltwin_data/containers/tray/tray.jpg
digitaltwin_data/containers/tray/tray.urdf
digitaltwin_data/containers/tray/tray_textured.mtl
digitaltwin_data/containers/tray/tray_textured.obj
digitaltwin_data/containers/tray/tray_textured2.mtl
digitaltwin_data/containers/tray/tray_textured2.obj
digitaltwin_data/containers/tray/tray_textured2.urdf
digitaltwin_data/containers/tray/tray_textured4.mtl
digitaltwin_data/containers/tray/tray_textured4.obj
digitaltwin_data/containers/tray/traybox.urdf
digitaltwin_data/containers/woodboard/Material_BaseColor.jpg
digitaltwin_data/containers/woodboard/woodboard.mtl
digitaltwin_data/containers/woodboard/woodboard.obj
digitaltwin_data/containers/woodboard/woodboard.urdf
digitaltwin_data/end_effectors/gripper_gp12/base.mtl
digitaltwin_data/end_effectors/gripper_gp12/base.obj
digitaltwin_data/end_effectors/gripper_gp12/finger_l.mtl
digitaltwin_data/end_effectors/gripper_gp12/finger_l.obj
digitaltwin_data/end_effectors/gripper_gp12/finger_r.mtl
digitaltwin_data/end_effectors/gripper_gp12/finger_r.obj
digitaltwin_data/end_effectors/gripper_gp12/gripper_gp12.urdf
digitaltwin_data/end_effectors/gripper_gp12-straight/base.mtl
digitaltwin_data/end_effectors/gripper_gp12-straight/base.obj
pysimflow-0.0.96.dist-info/METADATA
pysimflow-0.0.96.dist-info/WHEEL
pysimflow-0.0.96.dist-info/top_level.txt
pysimflow-0.0.96.dist-info/RECORD
