Metadata-Version: 2.1
Name: pysimflow
Version: 0.0.96
Summary: UNKNOWN
Home-page: UNKNOWN
Author: sl.truman
Author-email: sl.truman@live.com
License: UNKNOWN
Platform: UNKNOWN
Requires-Dist: numpy
Requires-Dist: pybullet
Requires-Dist: scipy
